nnest/__init__.py
nnest/mcmc.py
nnest/nested.py
nnest/networks.py
nnest/sampler.py
nnest/trainer.py
nnest/distributions/__init__.py
nnest/distributions/generalised_normal.py
nnest/utils/__init__.py
nnest/utils/evaluation.py
nnest/utils/logger.py
nnest-0.2.0.dist-info/LICENSE
nnest-0.2.0.dist-info/METADATA
nnest-0.2.0.dist-info/WHEEL
nnest-0.2.0.dist-info/top_level.txt
nnest-0.2.0.dist-info/RECORD
